fuzzingtool/__init__.py
fuzzingtool/api.py
fuzzingtool/fuzz_lib.py
fuzzingtool/fuzzingtool.py
fuzzingtool/conn/__init__.py
fuzzingtool/conn/request_parser.py
fuzzingtool/conn/requesters/__init__.py
fuzzingtool/conn/requesters/requester.py
fuzzingtool/conn/requesters/subdomain_requester.py
fuzzingtool/core/__init__.py
fuzzingtool/core/blacklist_status.py
fuzzingtool/core/dictionary.py
fuzzingtool/core/filter.py
fuzzingtool/core/fuzzer.py
fuzzingtool/core/job_manager.py
fuzzingtool/core/matcher.py
fuzzingtool/core/payloader.py
fuzzingtool/core/recursion_manager.py
fuzzingtool/core/summary.py
fuzzingtool/core/bases/__init__.py
fuzzingtool/core/bases/base_encoder.py
fuzzingtool/core/bases/base_observer.py
fuzzingtool/core/bases/base_plugin.py
fuzzingtool/core/bases/base_scanner.py
fuzzingtool/core/bases/base_validator.py
fuzzingtool/core/bases/base_wordlist.py
fuzzingtool/core/bases/job_provider.py
fuzzingtool/core/defaults/__init__.py
fuzzingtool/core/defaults/encoders/__init__.py
fuzzingtool/core/defaults/encoders/chain_encoder.py
fuzzingtool/core/defaults/scanners/__init__.py
fuzzingtool/core/defaults/scanners/data_scanner.py
fuzzingtool/core/defaults/scanners/path_scanner.py
fuzzingtool/core/defaults/scanners/subdomain_scanner.py
fuzzingtool/core/defaults/wordlists/__init__.py
fuzzingtool/core/defaults/wordlists/file_wordlist.py
fuzzingtool/core/defaults/wordlists/list_wordlist.py
fuzzingtool/core/plugins/__init__.py
fuzzingtool/core/plugins/encoders/__init__.py
fuzzingtool/core/plugins/encoders/base64.py
fuzzingtool/core/plugins/encoders/hex.py
fuzzingtool/core/plugins/encoders/html.py
fuzzingtool/core/plugins/encoders/html_dec.py
fuzzingtool/core/plugins/encoders/html_hex.py
fuzzingtool/core/plugins/encoders/plain.py
fuzzingtool/core/plugins/encoders/url.py
fuzzingtool/core/plugins/scanners/__init__.py
fuzzingtool/core/plugins/scanners/backups.py
fuzzingtool/core/plugins/scanners/grep.py
fuzzingtool/core/plugins/scanners/reflected.py
FuzzingTool-3.14.0.dist-info/LICENSE
FuzzingTool-3.14.0.dist-info/METADATA
FuzzingTool-3.14.0.dist-info/WHEEL
FuzzingTool-3.14.0.dist-info/entry_points.txt
FuzzingTool-3.14.0.dist-info/top_level.txt
FuzzingTool-3.14.0.dist-info/RECORD
