Metadata-Version: 2.1
Name: FuzzingTool
Version: 3.14.0
Summary: Software for fuzzing, used on web application pentestings.
Home-page: https://github.com/NESCAU-UFLA/FuzzingTool/
Author: Vitor Oriel C N Borges
Author-email: vitorwixmix@gmail.com
License: MIT
Keywords: pentesting-tools python3 fuzzing web-security
Platform: UNKNOWN
Classifier: Development Status :: 4 - Beta
Classifier: Natural Language :: English
Classifier: License :: OSI Approved :: MIT License
Classifier: Operating System :: POSIX :: Linux
Classifier: Programming Language :: Python :: 3.6
Classifier: Programming Language :: Python :: 3.7
Classifier: Programming Language :: Python :: 3.8
Classifier: Programming Language :: Python :: 3.9
Requires-Python: >=3.6
Requires-Dist: beautifulsoup4 (>=4.9.3)
Requires-Dist: dnspython (>=2.1.0)
Requires-Dist: python-Wappalyzer (>=0.3.1)
Requires-Dist: requests (>=2.25.1)
Provides-Extra: dev
Requires-Dist: pytest ; extra == 'dev'
Requires-Dist: pytest-cov ; extra == 'dev'
